odoo8_addon_auth_supplier-8.0.1.0.0.99.dev26-py2.7-nspkg.pth
odoo8_addon_auth_supplier-8.0.1.0.0.99.dev26.dist-info/DESCRIPTION.rst
odoo8_addon_auth_supplier-8.0.1.0.0.99.dev26.dist-info/METADATA
odoo8_addon_auth_supplier-8.0.1.0.0.99.dev26.dist-info/RECORD
odoo8_addon_auth_supplier-8.0.1.0.0.99.dev26.dist-info/WHEEL
odoo8_addon_auth_supplier-8.0.1.0.0.99.dev26.dist-info/metadata.json
odoo8_addon_auth_supplier-8.0.1.0.0.99.dev26.dist-info/namespace_packages.txt
odoo8_addon_auth_supplier-8.0.1.0.0.99.dev26.dist-info/top_level.txt
odoo_addons/auth_supplier/README.rst
odoo_addons/auth_supplier/__init__.py
odoo_addons/auth_supplier/__openerp__.py
odoo_addons/auth_supplier/controllers/__init__.py
odoo_addons/auth_supplier/controllers/main.py
odoo_addons/auth_supplier/i18n/ar.po
odoo_addons/auth_supplier/i18n/auth_supplier.pot
odoo_addons/auth_supplier/i18n/bg.po
odoo_addons/auth_supplier/i18n/ca.po
odoo_addons/auth_supplier/i18n/da.po
odoo_addons/auth_supplier/i18n/de.po
odoo_addons/auth_supplier/i18n/el_GR.po
odoo_addons/auth_supplier/i18n/es.po
odoo_addons/auth_supplier/i18n/es_ES.po
odoo_addons/auth_supplier/i18n/es_MX.po
odoo_addons/auth_supplier/i18n/eu_ES.po
odoo_addons/auth_supplier/i18n/fi.po
odoo_addons/auth_supplier/i18n/fr.po
odoo_addons/auth_supplier/i18n/fr_CH.po
odoo_addons/auth_supplier/i18n/fr_FR.po
odoo_addons/auth_supplier/i18n/gl.po
odoo_addons/auth_supplier/i18n/hr.po
odoo_addons/auth_supplier/i18n/hr_HR.po
odoo_addons/auth_supplier/i18n/it.po
odoo_addons/auth_supplier/i18n/nl.po
odoo_addons/auth_supplier/i18n/nl_NL.po
odoo_addons/auth_supplier/i18n/pt_BR.po
odoo_addons/auth_supplier/i18n/pt_PT.po
odoo_addons/auth_supplier/i18n/sk.po
odoo_addons/auth_supplier/i18n/sl.po
odoo_addons/auth_supplier/i18n/tr.po
odoo_addons/auth_supplier/i18n/tr_TR.po
odoo_addons/auth_supplier/i18n/zh_CN.po
odoo_addons/auth_supplier/models/__init__.py
odoo_addons/auth_supplier/models/res_users.py
odoo_addons/auth_supplier/security/auth_supplier_security.xml
odoo_addons/auth_supplier/static/description/icon.png
odoo_addons/auth_supplier/tests/__init__.py
odoo_addons/auth_supplier/tests/test_auth_supplier.py
odoo_addons/auth_supplier/views/auth_supplier_view.xml
